nvdiffrast/__init__.py
nvdiffrast/common/antialias.cu
nvdiffrast/common/antialias.h
nvdiffrast/common/common.cpp
nvdiffrast/common/common.h
nvdiffrast/common/framework.h
nvdiffrast/common/glutil.cpp
nvdiffrast/common/glutil.h
nvdiffrast/common/glutil_extlist.h
nvdiffrast/common/interpolate.cu
nvdiffrast/common/interpolate.h
nvdiffrast/common/rasterize.cu
nvdiffrast/common/rasterize.h
nvdiffrast/common/rasterize_gl.cpp
nvdiffrast/common/rasterize_gl.h
nvdiffrast/common/texture.cpp
nvdiffrast/common/texture.cu
nvdiffrast/common/texture.h
nvdiffrast/common/cudaraster/CudaRaster.hpp
nvdiffrast/common/cudaraster/impl/BinRaster.inl
nvdiffrast/common/cudaraster/impl/Buffer.cpp
nvdiffrast/common/cudaraster/impl/Buffer.hpp
nvdiffrast/common/cudaraster/impl/CoarseRaster.inl
nvdiffrast/common/cudaraster/impl/Constants.hpp
nvdiffrast/common/cudaraster/impl/CudaRaster.cpp
nvdiffrast/common/cudaraster/impl/Defs.hpp
nvdiffrast/common/cudaraster/impl/FineRaster.inl
nvdiffrast/common/cudaraster/impl/PrivateDefs.hpp
nvdiffrast/common/cudaraster/impl/RasterImpl.cpp
nvdiffrast/common/cudaraster/impl/RasterImpl.cu
nvdiffrast/common/cudaraster/impl/RasterImpl.hpp
nvdiffrast/common/cudaraster/impl/TriangleSetup.inl
nvdiffrast/common/cudaraster/impl/Util.inl
nvdiffrast/lib/setgpu.lib
nvdiffrast/tensorflow/__init__.py
nvdiffrast/tensorflow/ops.py
nvdiffrast/tensorflow/plugin_loader.py
nvdiffrast/tensorflow/tf_all.cu
nvdiffrast/tensorflow/tf_antialias.cu
nvdiffrast/tensorflow/tf_interpolate.cu
nvdiffrast/tensorflow/tf_rasterize.cu
nvdiffrast/tensorflow/tf_texture.cu
nvdiffrast/torch/__init__.py
nvdiffrast/torch/ops.py
nvdiffrast/torch/torch_antialias.cpp
nvdiffrast/torch/torch_bindings.cpp
nvdiffrast/torch/torch_bindings_gl.cpp
nvdiffrast/torch/torch_common.inl
nvdiffrast/torch/torch_interpolate.cpp
nvdiffrast/torch/torch_rasterize.cpp
nvdiffrast/torch/torch_rasterize_gl.cpp
nvdiffrast/torch/torch_texture.cpp
nvdiffrast/torch/torch_types.h
diffrp_nvdiffrast-0.3.3.1.dist-info/LICENSE.txt
diffrp_nvdiffrast-0.3.3.1.dist-info/METADATA
diffrp_nvdiffrast-0.3.3.1.dist-info/WHEEL
diffrp_nvdiffrast-0.3.3.1.dist-info/top_level.txt
diffrp_nvdiffrast-0.3.3.1.dist-info/RECORD
