Metadata-Version: 2.1
Name: diffrp-nvdiffrast
Version: 0.3.3.1
Summary: nvdiffrast - modular primitives for high-performance differentiable rendering
Home-page: https://github.com/NVlabs/nvdiffrast
Author: Samuli Laine
Author-email: slaine@nvidia.com
Classifier: Programming Language :: Python :: 3
Classifier: Operating System :: OS Independent
Requires-Python: >=3.6
License-File: LICENSE.txt
Requires-Dist: numpy
